[{"word":"KUVAT", "x":6.2, "y":55.5, "w":5.4, "h":1.2},
{"word":"Aosta", "x":15.5, "y":77.8, "w":4.4, "h":1},
{"word":"Chivasso", "x":26, "y":71.9, "w":6.8, "h":1},
{"word":"TORINO", "x":20, "y":71.1, "w":6, "h":1},
{"word":"MILANO", "x":35.2, "y":75.1, "w":6.4, "h":1},
{"word":"Milano", "x":35.9, "y":73.5, "w":5.3, "h":1},
{"word":"st.", "x":41.6, "y":73.5, "w":1.8, "h":1},
{"word":"Malpensa", "x":28.3, "y":76.7, "w":7.4, "h":1},
{"word":"PÄIVÄ", "x":6, "y":38.6, "w":7.9, "h":1.6},
{"word":"1", "x":14.6, "y":38.6, "w":1.5, "h":1.6},
{"word":"|", "x":17.6, "y":38.6, "w":0.7, "h":1.6},
{"word":"Helsinki", "x":19, "y":38.6, "w":10.3, "h":1.6},
{"word":"-", "x":30.1, "y":38.6, "w":0.8, "h":1.6},
{"word":"Aosta", "x":31.6, "y":38.6, "w":7.5, "h":1.6},
{"word":"Finnairin", "x":6, "y":35.4, "w":8, "h":1.2},
{"word":"aamulennolla", "x":14.5, "y":35.4, "w":12.3, "h":1.2},
{"word":"laskeuduimme", "x":27.2, "y":35.4, "w":-10.5, "h":1.2},
{"word":"Milano", "x":17.2, "y":33.7, "w":5.7, "h":1.2},
{"word":"Malpensan", "x":23.4, "y":33.7, "w":9.2, "h":1.2},
{"word":"kentälle", "x":6, "y":32, "w":6.6, "h":1.2},
{"word":"jo", "x":13.1, "y":32, "w":1.5, "h":1.2},
{"word":"kymmenen", "x":15.1, "y":32, "w":9.5, "h":1.2},
{"word":"jälkeen", "x":25.1, "y":32, "w":6, "h":1.2},
{"word":"aamulla.", "x":6, "y":30.3, "w":7, "h":1.2},
{"word":"Milanon", "x":13.5, "y":30.3, "w":6.9, "h":1.2},
{"word":"kentältä", "x":20.8, "y":30.3, "w":6.8, "h":1.2},
{"word":"löytyi", "x":28.1, "y":30.3, "w":4.6, "h":1.2},
{"word":"helposti", "x":6, "y":28.6, "w":6.7, "h":1.2},
{"word":"juna-asema", "x":13.2, "y":28.6, "w":9.7, "h":1.2},
{"word":"ja", "x":23.4, "y":28.6, "w":1.4, "h":1.2},
{"word":"automaatista", "x":25.3, "y":28.6, "w":-15.8, "h":1.2},
{"word":"saimme", "x":10, "y":26.9, "w":6.6, "h":1.2},
{"word":"ostettua", "x":17, "y":26.9, "w":6.9, "h":1.2},
{"word":"liput", "x":24.5, "y":26.9, "w":3.8, "h":1.2},
{"word":"kohti", "x":28.8, "y":26.9, "w":4.3, "h":1.2},
{"word":"Milanon", "x":6, "y":25.2, "w":6.9, "h":1.2},
{"word":"päärautatieasemaa.", "x":13.3, "y":25.2, "w":16.4, "h":1.2},
{"word":"Päärautatieasemalta", "x":6, "y":23.4, "w":17, "h":1.2},
{"word":"ostimme", "x":23.4, "y":23.4, "w":7.4, "h":1.2},
{"word":"junaliput", "x":6, "y":21.7, "w":7.5, "h":1.2},
{"word":"Aostaan", "x":14, "y":21.7, "w":6.8, "h":1.2},
{"word":"(1", "x":21.3, "y":21.7, "w":1.6, "h":1.2},
{"word":"vaihto", "x":23.3, "y":21.7, "w":5.2, "h":1.2},
{"word":"chivassossa).", "x":6, "y":20, "w":10.6, "h":1.2},
{"word":"Kolmessa", "x":17.1, "y":20, "w":7.9, "h":1.2},
{"word":"eri", "x":25.5, "y":20, "w":2.1, "h":1.2},
{"word":"junassa,", "x":28.1, "y":20, "w":-19.9, "h":1.2},
{"word":"yhteensä", "x":8.6, "y":18.3, "w":7.6, "h":1.2},
{"word":"noin", "x":16.7, "y":18.3, "w":3.8, "h":1.2},
{"word":"neljä", "x":20.9, "y":18.3, "w":4, "h":1.2},
{"word":"tuntia", "x":25.4, "y":18.3, "w":4.9, "h":1.2},
{"word":"istuttuamme", "x":6, "y":16.6, "w":10.8, "h":1.2},
{"word":"saavutimme", "x":17.3, "y":16.6, "w":10.3, "h":1.2},
{"word":"Aostan", "x":28, "y":16.6, "w":5.8, "h":1.2},
{"word":"aseman", "x":6, "y":14.9, "w":6.5, "h":1.2},
{"word":"ja", "x":13, "y":14.9, "w":1.4, "h":1.2},
{"word":"aurinkoiset", "x":14.9, "y":14.9, "w":9.3, "h":1.2},
{"word":"kävelykadut", "x":24.6, "y":14.9, "w":-15.8, "h":1.2},
{"word":"n.", "x":9.3, "y":13.2, "w":1.5, "h":1.2},
{"word":"klo", "x":11.3, "y":13.2, "w":2.5, "h":1.2},
{"word":"16.", "x":14.3, "y":13.2, "w":2.4, "h":1.2},
{"word":"Ensimmäinen", "x":8.4, "y":11.5, "w":11.4, "h":1.2},
{"word":"majoituksemme", "x":20.2, "y":11.5, "w":13.6, "h":1.2},
{"word":"oli", "x":6, "y":9.8, "w":2, "h":1.2},
{"word":"asemalta", "x":8.5, "y":9.8, "w":7.5, "h":1.2},
{"word":"katsottuna", "x":16.5, "y":9.8, "w":9, "h":1.2},
{"word":"aivan", "x":25.9, "y":9.8, "w":4.4, "h":1.2},
{"word":"toisella", "x":6, "y":8, "w":5.9, "h":1.2},
{"word":"puolella", "x":12.4, "y":8, "w":6.7, "h":1.2},
{"word":"kaupunkia,", "x":19.6, "y":8, "w":9.2, "h":1.2},
{"word":"joten", "x":29.3, "y":8, "w":4.3, "h":1.2},
{"word":"tetsaaminen", "x":36, "y":35.4, "w":10.4, "h":1.2},
{"word":"n.", "x":46.9, "y":35.4, "w":1.5, "h":1.2},
{"word":"20", "x":48.8, "y":35.4, "w":2, "h":1.2},
{"word":"kg", "x":51.3, "y":35.4, "w":2, "h":1.2},
{"word":"rollereiden", "x":53.8, "y":35.4, "w":9, "h":1.2},
{"word":"ja", "x":36, "y":33.7, "w":1.4, "h":1.2},
{"word":"turpeiden", "x":37.9, "y":33.7, "w":8.3, "h":1.2},
{"word":"reppujen", "x":46.6, "y":33.7, "w":7.6, "h":1.2},
{"word":"kanssa", "x":54.7, "y":33.7, "w":5.6, "h":1.2},
{"word":"kävi", "x":36, "y":32, "w":3.3, "h":1.2},
{"word":"työstä.", "x":39.8, "y":32, "w":5.5, "h":1.2},
{"word":"Etenkin", "x":45.8, "y":32, "w":6.3, "h":1.2},
{"word":"kun", "x":52.5, "y":32, "w":3.1, "h":1.2},
{"word":"olimme", "x":56.2, "y":32, "w":6.4, "h":1.2},
{"word":"pukeutuneet", "x":36, "y":30.3, "w":10.9, "h":1.2},
{"word":"laksureissuun", "x":47.3, "y":30.3, "w":11.3, "h":1.2},
{"word":"ja", "x":59.1, "y":30.3, "w":1.4, "h":1.2},
{"word":"Aostan", "x":36, "y":28.6, "w":5.8, "h":1.2},
{"word":"kaupungissa", "x":42.3, "y":28.6, "w":10.5, "h":1.2},
{"word":"oli", "x":53.3, "y":28.6, "w":2, "h":1.2},
{"word":"miltei", "x":55.8, "y":28.6, "w":4.7, "h":1.2},
{"word":"kesä.", "x":36, "y":26.9, "w":4.1, "h":1.2},
{"word":"Kahden", "x":38.4, "y":25.2, "w":6.4, "h":1.2},
{"word":"makuuhuoneen", "x":45.3, "y":25.2, "w":13.4, "h":1.2},
{"word":"asunto", "x":36, "y":23.4, "w":5.7, "h":1.2},
{"word":"oli", "x":42.2, "y":23.4, "w":2, "h":1.2},
{"word":"meille", "x":44.6, "y":23.4, "w":5.1, "h":1.2},
{"word":"oikein", "x":50.2, "y":23.4, "w":5.1, "h":1.2},
{"word":"passeli", "x":55.7, "y":23.4, "w":5.6, "h":1.2},
{"word":"ja", "x":61.8, "y":23.4, "w":1.4, "h":1.2},
{"word":"vaihdettuamme", "x":36, "y":21.7, "w":13.4, "h":1.2},
{"word":"ennalta", "x":49.9, "y":21.7, "w":6.3, "h":1.2},
{"word":"sovitun", "x":56.6, "y":21.7, "w":-17.8, "h":1.2},
{"word":"summan", "x":39.3, "y":20, "w":7.3, "h":1.2},
{"word":"vuokraajan", "x":47.1, "y":20, "w":9.3, "h":1.2},
{"word":"kanssa", "x":56.9, "y":20, "w":5.6, "h":1.2},
{"word":"avaimiin,", "x":36, "y":18.3, "w":7.5, "h":1.2},
{"word":"pääsimme", "x":43.9, "y":18.3, "w":8.7, "h":1.2},
{"word":"etsimään", "x":53.1, "y":18.3, "w":7.6, "h":1.2},
{"word":"lähimmän", "x":36, "y":16.6, "w":8.4, "h":1.2},
{"word":"supermarketin.", "x":44.9, "y":16.6, "w":12.6, "h":1.2},
{"word":"Lautapummailun", "x":38.4, "y":14.9, "w":14.4, "h":1.2},
{"word":"hengessä", "x":53.2, "y":14.9, "w":7.9, "h":1.2},
{"word":"suunnitelmana", "x":36, "y":13.2, "w":12.6, "h":1.2},
{"word":"oli", "x":49, "y":13.2, "w":2, "h":1.2},
{"word":"elää", "x":51.5, "y":13.2, "w":3.4, "h":1.2},
{"word":"nämä", "x":55.3, "y":13.2, "w":4.7, "h":1.2},
{"word":"ensimmäiset", "x":36, "y":11.5, "w":10.6, "h":1.2},
{"word":"kolme", "x":47.1, "y":11.5, "w":5.2, "h":1.2},
{"word":"viikkoa", "x":52.7, "y":11.5, "w":5.9, "h":1.2},
{"word":"säästäen", "x":36, "y":9.8, "w":7.3, "h":1.2},
{"word":"kaikessa", "x":43.7, "y":9.8, "w":6.9, "h":1.2},
{"word":"muussa", "x":51.1, "y":9.8, "w":6.4, "h":1.2},
{"word":"paitsi", "x":58, "y":9.8, "w":4.5, "h":1.2},
{"word":"laskupäivissä,", "x":36, "y":8, "w":11.3, "h":1.2},
{"word":"tehdä", "x":47.7, "y":8, "w":4.8, "h":1.2},
{"word":"ruoka", "x":53, "y":8, "w":4.8, "h":1.2},
{"word":"itse", "x":58.3, "y":8, "w":2.9, "h":1.2},
{"word":"ja", "x":65.9, "y":35.4, "w":1.4, "h":1.2},
{"word":"syödä", "x":67.8, "y":35.4, "w":4.9, "h":1.2},
{"word":"rinteessäkin", "x":73.2, "y":35.4, "w":10, "h":1.2},
{"word":"pääosin", "x":83.7, "y":35.4, "w":6.5, "h":1.2},
{"word":"eväitä,", "x":65.9, "y":33.7, "w":5.4, "h":1.2},
{"word":"toki", "x":71.8, "y":33.7, "w":3.2, "h":1.2},
{"word":"kieltämättä", "x":75.5, "y":33.7, "w":9.5, "h":1.2},
{"word":"itseltämme", "x":85.4, "y":33.7, "w":-16.9, "h":1.2},
{"word":"silloin", "x":69.1, "y":32, "w":4.9, "h":1.2},
{"word":"tällöin", "x":74.4, "y":32, "w":5.2, "h":1.2},
{"word":"nautinnollista", "x":80.1, "y":32, "w":11.5, "h":1.2},
{"word":"olutta", "x":65.9, "y":30.3, "w":4.9, "h":1.2},
{"word":"ja", "x":71.4, "y":30.3, "w":1.4, "h":1.2},
{"word":"kaakaota,", "x":73.3, "y":30.3, "w":8, "h":1.2},
{"word":"pizzan", "x":81.7, "y":30.3, "w":5.4, "h":1.2},
{"word":"palaa", "x":87.6, "y":30.3, "w":4.5, "h":1.2},
{"word":"tai", "x":65.9, "y":28.6, "w":2.1, "h":1.2},
{"word":"ranskalaisia", "x":68.5, "y":28.6, "w":9.6, "h":1.2},
{"word":"rinneravintoloiden", "x":78.6, "y":28.6, "w":-9.4, "h":1.2},
{"word":"aurinkoisilla", "x":69.6, "y":26.9, "w":10, "h":1.2},
{"word":"terasseilla.", "x":80.1, "y":26.9, "w":8.7, "h":1.2},
{"word":"Ensimmäisenä", "x":68.3, "y":25.2, "w":12, "h":1.2},
{"word":"iltana", "x":80.8, "y":25.2, "w":4.6, "h":1.2},
{"word":"löysimme", "x":85.9, "y":25.2, "w":-17.4, "h":1.2},
{"word":"kaupasta", "x":69.1, "y":23.4, "w":7.6, "h":1.2},
{"word":"pastaa,", "x":77.1, "y":23.4, "w":5.9, "h":1.2},
{"word":"jauhelihaa", "x":83.5, "y":23.4, "w":8.7, "h":1.2},
{"word":"ja", "x":65.9, "y":21.7, "w":1.4, "h":1.2},
{"word":"purkkitomaattikasktiketta.", "x":68.3, "y":21.7, "w":22, "h":1.2},
{"word":"Tämä", "x":65.9, "y":20, "w":4.4, "h":1.2},
{"word":"kolminaisuus", "x":70.9, "y":20, "w":11, "h":1.2},
{"word":"osui", "x":82.4, "y":20, "w":3.4, "h":1.2},
{"word":"etenkin", "x":86.3, "y":20, "w":6.3, "h":1.2},
{"word":"Siirille", "x":65.9, "y":18.3, "w":5, "h":1.2},
{"word":"niin", "x":71.4, "y":18.3, "w":3.1, "h":1.2},
{"word":"hyvin,", "x":75, "y":18.3, "w":5, "h":1.2},
{"word":"että", "x":80.5, "y":18.3, "w":3.3, "h":1.2},
{"word":"siitä", "x":84.2, "y":18.3, "w":3.3, "h":1.2},
{"word":"mudostuikin", "x":88, "y":18.3, "w":-14.3, "h":1.2},
{"word":"sitten", "x":74.2, "y":16.6, "w":4.7, "h":1.2},
{"word":"koko", "x":79.4, "y":16.6, "w":4.1, "h":1.2},
{"word":"kuukauden", "x":83.9, "y":16.6, "w":9.5, "h":1.2},
{"word":"kulinaristinen", "x":65.9, "y":14.9, "w":11.4, "h":1.2},
{"word":"perusruokamme,", "x":77.8, "y":14.9, "w":14.3, "h":1.2},
{"word":"johon", "x":65.9, "y":13.2, "w":4.9, "h":1.2},
{"word":"vain", "x":71.3, "y":13.2, "w":3.5, "h":1.2},
{"word":"harvoin", "x":75.3, "y":13.2, "w":6.4, "h":1.2},
{"word":"haimme", "x":82.1, "y":13.2, "w":6.9, "h":1.2},
{"word":"vaihtelua", "x":65.9, "y":11.5, "w":7.7, "h":1.2},
{"word":"pakastepizzoista", "x":74.1, "y":11.5, "w":13.8, "h":1.2},
{"word":"tai", "x":88.4, "y":11.5, "w":2.1, "h":1.2},
{"word":"kana-salaatista.", "x":65.9, "y":9.8, "w":12.8, "h":1.2},
{}]